inputconditioner.v
//------------------------------------------------------------------------
// Input Conditioner
//    1) Synchronizes input to clock domain
//    2) Debounces input
//    3) Creates pulses at edge transitions
//------------------------------------------------------------------------

module inputconditioner
(
input 	    clk,            // Clock domain to synchronize input to
input	    noisysignal,    // (Potentially) noisy input signal
output reg  conditioned,    // Conditioned output signal
output reg  positiveedge,   // 1 clk pulse at rising edge of conditioned
output reg  negativeedge    // 1 clk pulse at falling edge of conditioned
);

    parameter counterwidth = 3; // Counter size, in bits, >= log2(waittime)
    parameter waittime = 3;     // Debounce delay, in clock cycles
    
    reg[counterwidth-1:0] counter = 0;
    reg synchronizer0 = 0;
    reg synchronizer1 = 0;
    
    always @(posedge clk ) begin
        if(conditioned == synchronizer1)
            counter <= 0;
        else begin
            if( counter == waittime) begin
                counter <= 0;
                conditioned <= synchronizer1;
            end
            else 
                counter <= counter+1;
        end
        synchronizer0 <= noisysignal;
        synchronizer1 <= synchronizer0;
    end



    // At the positive edge, set positivedge to high
    always @(posedge clk) begin
        positiveedge <= 1;
        negativeedge <= 0;
    end

    // At the negative edge, set negativedge to high
    always @(negedge clk) begin
        positiveedge <= 0;
        negativeedge <= 1;
    end



endmodule

inputconditioner.t.v
//------------------------------------------------------------------------
// Input Conditioner test bench
//------------------------------------------------------------------------
`include "inputconditioner.v"
// `timescale 1ns/1ps
module testConditioner();

    reg clk;
    reg noisysignal;
    wire conditioned;
    wire rising;
    wire falling;
    
    
    inputconditioner inputconditionerDUT
    (
        .clk(clk),
        .noisysignal (noisysignal),
        .conditioned(conditioned),
        .positiveedge(rising),
        .negativeedge(falling)
    );


      // Test harness asserts 'begintest' for 1000 time steps, starting at time 10


    initial begin
        $dumpfile("inputconditioner.vcd");
        $dumpvars();
        noisysignal = 0;
        clk=0;
    end

    // Generate clock (50MHz)
    initial clk = 0;
    always #10 clk = !clk;    // 50MHz Clock


    initial begin


        noisysignal = 0;#5
        
        noisysignal = 1;#20

        if(( conditioned != 1 )) begin
            $display("Conditioned Test case 1 Failed");
        end


        
        noisysignal = 0;#20

        if(( conditioned != 0 )) begin
            $display("Conditioned Test case 2 Failed");
        end



        noisysignal = 1; #5

        if(( inputconditionerDUT.synchronizer0 == 1 )) begin
            $display("Sync Test case 3 Failed");
        end

        #15

        if(( inputconditionerDUT.synchronizer1 == 1 )) begin
            $display("Sync Test case 4 Failed");
        end


        noisysignal = 0; #300
        noisysignal = 1; #5
        noisysignal = 0; #5
        noisysignal = 1; #5
        noisysignal = 0; #5
        noisysignal = 1; #250

        // Expect the conditioned output to be high when the pin input has stabilized.
        if (conditioned != 1) begin
            $display("Debouncing to Rest High Test Case 5 failed.");
        end


        #5
        $finish();
    end
        

        always @(posedge conditioned) begin
            #5;
            if (rising != 1 && $time > 100) begin
                $display("Positive Edge Test Case 6 failed");
            end
        end
        

        always @(negedge conditioned) begin
            #5;
            if (falling != 1 && $time > 100) begin
                $display("Negative Edge Test Case 7 failed");
            end
        end

        

        
endmodule

inputconditioner.vcd
$date
	Mon Oct 15 21:32:12 2018
$end
$version
	Icarus Verilog
$end
$timescale
	1s
$end
$scope module testConditioner $end
$var wire 1 ! rising $end
$var wire 1 " falling $end
$var wire 1 # conditioned $end
$var reg 1 $ clk $end
$var reg 1 % noisysignal $end
$scope module inputconditionerDUT $end
$var wire 1 $ clk $end
$var wire 1 % noisysignal $end
$var reg 1 # conditioned $end
$var reg 3 & counter [2:0] $end
$var reg 1 " negativeedge $end
$var reg 1 ! positiveedge $end
$var reg 1 ' synchronizer0 $end
$var reg 1 ( synchronizer1 $end
$upscope $end
$upscope $end
$enddefinitions $end
#0
$dumpvars
0(
0'
b0 &
0%
0$
x#
x"
x!
$end
#5
1%
#10
1'
b1 &
0"
0!
1$
#20
0$
#25
0%
#30
1(
0'
b10 &
1$
#40
0$
#45
1%
#50
0(
1'
b11 &
1$
#60
0$
#65
0%
#70
1(
0'
0#
b0 &
1$
#80
0$
#90
0(
b1 &
1$
#100
0$
#110
b0 &
1$
#120
0$
#130
1$
#140
0$
#150
1$
#160
0$
#170
1$
#180
0$
#190
1$
#200
0$
#210
1$
#220
0$
#230
1$
#240
0$
#250
1$
#260
0$
#270
1$
#280
0$
#290
1$
#300
0$
#310
1$
#320
0$
#330
1$
#340
0$
#350
1$
#360
0$
#365
1%
#370
0%
1$
#375
1%
#380
0%
0$
#385
1%
#390
1'
1$
#400
0$
#410
1(
1$
#420
0$
#430
b1 &
1$
#440
0$
#450
b10 &
1$
#460
0$
#470
b11 &
1$
#480
0$
#490
1#
1!
b0 &
1$
#500
0$
#510
0!
1$
