shiftregister.v
//------------------------------------------------------------------------
// Shift Register
//   Parameterized width (in bits)
//   Shift register can operate in two modes:
//      - serial in, parallel out
//      - parallel in, serial out
//------------------------------------------------------------------------

module shiftregister
#(parameter width = 8)
(
input               clk,                // FPGA Clock
input               peripheralClkEdge,  // Edge indicator
input               parallelLoad,       // 1 = Load shift reg with parallelDataIn
input  [width-1:0]  parallelDataIn,     // Load shift reg in parallel
input               serialDataIn,       // Load shift reg serially
output reg [width-1:0]  parallelDataOut,    // Shift reg data contents
output reg             serialDataOut       // Positdive edge synchronized
);

    //reg [width:0]        shiftregistertemp;
    reg [width-1:0]      shiftregistermem;
    always @(posedge clk) begin

      if (parallelLoad) begin
        // take the value of parallelDataIn when parallelLoad is asserted
        shiftregistermem <= parallelDataIn;
      end
      else if (peripheralClkEdge) begin
        // advance the shift register one position, putting serialData in lsb
        shiftregistermem <= {shiftregistermem[width-2:0], serialDataIn};
        // get rid of the msb that has been shifted out of the frame
        //shiftregistermem <= shiftregistertemp[width-1:0];
      end

      // store the msb in serialDataOut
      serialDataOut <= parallelDataOut[width-1];
      parallelDataOut <= shiftregistermem;
    end

endmodule

shiftregister.t.v
`include "shiftregister.v"
`timescale 1ns/1ps
// Shift Register test bench
module testshiftregister();

    reg             clk;
    reg             peripheralClkEdge;
    reg             parallelLoad;
    wire[7:0]       parallelDataOut;
    wire            serialDataOut;
    reg[7:0]        parallelDataIn;
    reg             serialDataIn;

    // Instantiate with parameter width = 8
    shiftregister #(8) dut(.clk(clk),
    		           .peripheralClkEdge(peripheralClkEdge),
    		           .parallelLoad(parallelLoad),
    		           .parallelDataIn(parallelDataIn),
    		           .serialDataIn(serialDataIn),
    		           .parallelDataOut(parallelDataOut),
    		           .serialDataOut(serialDataOut));

    initial clk=0;
    always #10 clk=!clk;


    initial begin
    	parallelDataIn = 8'b11001100;
        parallelLoad = 1'b1;
        peripheralClkEdge = 1'b1;
        serialDataIn = 1'b1;
    end

endmodule

shiftregister.vcd
$date
	Wed Oct 10 22:15:47 2018
$end
$version
	Icarus Verilog
$end
$timescale
	1s
$end
$scope module testshiftregister $end
$var wire 1 ! serialDataOut $end
$var wire 8 " parallelDataOut [7:0] $end
$var reg 1 # clk $end
$var reg 8 $ parallelDataIn [7:0] $end
$var reg 1 % parallelLoad $end
$var reg 1 & peripheralClkEdge $end
$var reg 1 ' serialDataIn $end
$scope module dut $end
$var wire 1 # clk $end
$var wire 8 ( parallelDataIn [7:0] $end
$var wire 1 % parallelLoad $end
$var wire 1 & peripheralClkEdge $end
$var wire 1 ' serialDataIn $end
$var reg 8 ) parallelDataOut [7:0] $end
$var reg 1 ! serialDataOut $end
$var reg 8 * shiftregistermem [7:0] $end
$upscope $end
$upscope $end
$enddefinitions $end
#0
$dumpvars
bx *
bx )
bx (
0'
0&
0%
bx $
0#
bx "
x!
$end
#10
1#
#20
0#
#30
1#
#40
0#
#50
bx0 *
1#
1&
#60
0#
1'
0&
#70
bx0 "
bx0 )
1#
#80
0#
#90
1#
#100
0#
#110
bx01 *
1#
1&
#120
0#
0'
0&
#130
bx01 "
bx01 )
1#
#140
0#
#150
1#
#160
0#
#170
bx010 *
1#
1&
#180
0#
1'
0&
#190
bx010 "
bx010 )
1#
#200
0#
#210
1#
#220
0#
#230
bx0101 *
1#
1&
#240
0#
0'
0&
#250
bx0101 "
bx0101 )
1#
#260
0#
#270
1#
#280
0#
#290
bx01010 *
1#
1&
#300
0#
1'
0&
#310
bx01010 "
bx01010 )
1#
#320
0#
#330
1#
#340
0#
#350
bx010101 *
1#
1&
#360
0#
0'
0&
#370
bx010101 "
bx010101 )
1#
#380
0#
#390
1#
#400
0#
#410
bx0101010 *
1#
1&
#420
0#
1'
0&
#430
bx0101010 "
bx0101010 )
1#
#440
0#
#450
1#
#460
0#
#470
b1010101 *
1#
1&
#480
0#
0&
#490
b1010101 "
b1010101 )
1#
#500
0#
#510
0!
1#
#520
0#
#530
b10101011 *
1#
1&
#540
0#
0&
#550
b10101011 "
b10101011 )
1#
#560
0#
#570
1!
1#
