shiftregister.v
//------------------------------------------------------------------------
// Shift Register
//   Parameterized width (in bits)
//   Shift register can operate in two modes:
//      - serial in, parallel out
//      - parallel in, serial out
//------------------------------------------------------------------------

module shiftregister
#(parameter width = 8)
(
input               clk,                // FPGA Clock
input               peripheralClkEdge,  // Edge indicator
input               parallelLoad,       // 1 = Load shift reg with parallelDataIn
input  [width-1:0]  parallelDataIn,     // Load shift reg in parallel
input               serialDataIn,       // Load shift reg serially
output reg [width-1:0]  parallelDataOut,    // Shift reg data contents
output reg             serialDataOut       // Positive edge synchronized
);

    reg [width-1:0]      shiftregistermem;
    always @(posedge clk) begin

      if (parallelLoad) begin
        // take the value of parallelDataIn when parallelLoad is asserted
        shiftregistermem <= parallelDataIn;
      end
      else if (peripheralClkEdge) begin
        // advance the shift register one position, putting serialData in lsb
        shiftregistermem <= {shiftregistermem[width-2:0], serialDataIn};
      end

      // store the msb in serialDataOut
      parallelDataOut <= shiftregistermem;
      serialDataOut <= parallelDataOut[width-1];

    end

endmodule

shiftregister.t.v
`include "shiftregister.v"
`timescale 1ns/1ps
// Shift Register test bench
module testshiftregister();

    reg             clk;
    reg             peripheralClkEdge;      // 1 = you're at clock edge
    reg             parallelLoad;           // 1 = Load shift reg with parallelDataIn
    wire[7:0]       parallelDataOut;        // shifted reg data contents
    wire            serialDataOut;          // Positive edge synchronized
    reg[7:0]        parallelDataIn;         // load shift reg in parallel
    reg             serialDataIn;           // load shift reg in serial


    // Instantiate with parameter width = 8
    shiftregister #(8) dut
    (
        .clk(clk),
    	.peripheralClkEdge(peripheralClkEdge),
    	.parallelLoad(parallelLoad),
    	.parallelDataIn(parallelDataIn),
    	.serialDataIn(serialDataIn),
    	.parallelDataOut(parallelDataOut),
    	.serialDataOut(serialDataOut)
    );

initial clk=0;
always #10 clk=!clk;

initial begin
  $dumpfile("shiftregister.vcd");
  $dumpvars();

  // Test Case 1:
  // test serial input
  // Parallel = 10000000, Serial = 1
  // Parallel output = 00000001, seerial output = 0;
  parallelLoad = 1'b1;
  parallelDataIn = 8'b10000000; #20
  parallelLoad = 1'b0;
  peripheralClkEdge = 1;
  serialDataIn=1; #20

  if((parallelDataOut !== 8'b00000001) || (serialDataOut !== 0)) begin
      $display("Test Case 1 Failed %b %b", parallelDataOut, serialDataOut);
  end

  // Test Case 2:
  // test parallel input
  // Parallel = 10101011
  // Parallel output = 10101011, seerial output = 1;
  parallelLoad = 1'b1;
  parallelDataIn = 8'b10101011; #20

  if((parallelDataOut !== 8'b10101011) || (serialDataOut !== 1)) begin
      $display("Test Case 2 Failed %b %b", parallelDataOut, serialDataOut);
  end

  // Test Case 3:
  // load multiple serial values in a row
  // Parallel = 10000000, Serial = 1
  // Parallel output = 00000001, seerial output = 0;
  parallelLoad = 1'b1;
  parallelDataIn = 8'b10000000; #20
  parallelLoad = 1'b0;
  peripheralClkEdge = 1;
  serialDataIn=1; #20
  peripheralClkEdge = 1;
  serialDataIn=0; #20
  peripheralClkEdge = 1;
  serialDataIn=0; #20
  peripheralClkEdge = 1;
  serialDataIn=1; #20
  peripheralClkEdge = 1;
  serialDataIn=1; #20

  if((parallelDataOut !== 8'b00010011) || (serialDataOut !== 0)) begin
      $display("Test Case 3 Failed %b %b", parallelDataOut, serialDataOut);
  end


  $finish();


end

endmodule

shiftregister.vcd
$date
	Thu Oct 11 17:00:11 2018
$end
$version
	Icarus Verilog
$end
$timescale
	1ps
$end
$scope module testshiftregister $end
$var wire 1 ! serialDataOut $end
$var wire 8 " parallelDataOut [7:0] $end
$var reg 1 # clk $end
$var reg 8 $ parallelDataIn [7:0] $end
$var reg 1 % parallelLoad $end
$var reg 1 & peripheralClkEdge $end
$var reg 1 ' serialDataIn $end
$scope module dut $end
$var wire 1 # clk $end
$var wire 8 ( parallelDataIn [7:0] $end
$var wire 8 ) parallelDataOut [7:0] $end
$var wire 1 % parallelLoad $end
$var wire 1 & peripheralClkEdge $end
$var wire 1 ' serialDataIn $end
$var wire 1 ! serialDataOut $end
$var reg 8 * shiftregistermem [7:0] $end
$upscope $end
$upscope $end
$enddefinitions $end
#0
$dumpvars
bx *
bx )
b10000000 (
x'
x&
1%
b10000000 $
0#
bx "
x!
$end
#10000
1!
b10000000 "
b10000000 )
b10000000 *
1#
#20000
0#
1'
1&
0%
#30000
0!
b1 "
b1 )
b1 *
1#
#40000
0#
b10101011 $
b10101011 (
1%
#50000
1!
b10101011 "
b10101011 )
b10101011 *
1#
#60000
0#
b10000000 $
b10000000 (
#70000
b10000000 "
b10000000 )
b10000000 *
1#
#80000
0#
0%
#90000
0!
b1 "
b1 )
b1 *
1#
#100000
0#
0'
#110000
b10 "
b10 )
b10 *
1#
#120000
0#
#130000
b100 "
b100 )
b100 *
1#
#140000
0#
1'
#150000
b1001 "
b1001 )
b1001 *
1#
#160000
0#
#170000
b10011 "
b10011 )
b10011 *
1#
